wxautox_wechatbot/__init__.py
wxautox_wechatbot/comps.cp310-win_amd64.pyd
wxautox_wechatbot/languages.py
wxautox_wechatbot/logger.py
wxautox_wechatbot/msgs.cp310-win_amd64.pyd
wxautox_wechatbot/param.py
wxautox_wechatbot/ui.cp310-win_amd64.pyd
wxautox_wechatbot/uiautomation.py
wxautox_wechatbot/uiplug.cp310-win_amd64.pyd
wxautox_wechatbot/utils.cp310-win_amd64.pyd
wxautox_wechatbot/wx.cp310-win_amd64.pyd
wxautox_wechatbot-39.1.4.dist-info/entry_points.txt
wxautox_wechatbot-39.1.4.dist-info/LICENSE
wxautox_wechatbot-39.1.4.dist-info/METADATA
wxautox_wechatbot-39.1.4.dist-info/WHEEL
wxautox_wechatbot-39.1.4.dist-info/RECORD
