Metadata-Version: 2.3
Name: wxautox-wechatbot
Version: 39.1.4
Summary: wxauto 3.9 plus version for iwyxdxl/WeChatBot_WXAUTO_SE
Author: Cluic
Author-email: tikic@qq.com
Requires-Python: >=3.9,<3.13
Classifier: Programming Language :: Python :: 3
Classifier: Programming Language :: Python :: 3.9
Classifier: Programming Language :: Python :: 3.10
Classifier: Programming Language :: Python :: 3.11
Classifier: Programming Language :: Python :: 3.12
Requires-Dist: colorama
Requires-Dist: comtypes
Requires-Dist: pillow
Requires-Dist: psutil
Requires-Dist: pyperclip
Requires-Dist: pywin32
Requires-Dist: tenacity
